flask_topassets/__init__.py
flask_topassets-0.1.0.20250915.dist-info/licenses/LICENSE.txt
flask_topassets-0.1.0.20250915.dist-info/METADATA
flask_topassets-0.1.0.20250915.dist-info/WHEEL
flask_topassets-0.1.0.20250915.dist-info/top_level.txt
flask_topassets-0.1.0.20250915.dist-info/RECORD
