Metadata-Version: 2.4
Name: flask_topassets
Version: 0.1.0.20250915
Summary: a package on top of flask-assets
Author-email: lix <xuzenglin@gmail.com>
Project-URL: Homepage, https://github.com/lixxu/flask_topassets
Project-URL: Bug Tracker, https://github.com/lixxu/flask_topassets/issues
Keywords: flask-assets
Classifier: Intended Audience :: Developers
Classifier: Operating System :: OS Independent
Classifier: Programming Language :: Python :: 3
Classifier: Development Status :: 5 - Production/Stable
Requires-Python: >=3.10
License-File: LICENSE.txt
Requires-Dist: flask
Requires-Dist: flask_assets
Dynamic: license-file
